GuorenWangLianghuaKetangBangzhuWendang/README.md
GuorenWangLianghuaKetangBangzhuWendang/__init__.py
GuorenWangLianghuaKetangBangzhuWendang/__main__.py
GuorenWangLianghuaKetangBangzhuWendang/file.epub
GuorenWangLianghuaKetangBangzhuWendang/index.html
GuorenWangLianghuaKetangBangzhuWendang/css/__init__.py
GuorenWangLianghuaKetangBangzhuWendang/css/annotations.css
GuorenWangLianghuaKetangBangzhuWendang/css/main.css
GuorenWangLianghuaKetangBangzhuWendang/css/normalize.css
GuorenWangLianghuaKetangBangzhuWendang/css/popup.css
GuorenWangLianghuaKetangBangzhuWendang/font/__init__.py
GuorenWangLianghuaKetangBangzhuWendang/font/fontello.eot
GuorenWangLianghuaKetangBangzhuWendang/font/fontello.svg
GuorenWangLianghuaKetangBangzhuWendang/font/fontello.ttf
GuorenWangLianghuaKetangBangzhuWendang/font/fontello.woff
GuorenWangLianghuaKetangBangzhuWendang/img/__init__.py
GuorenWangLianghuaKetangBangzhuWendang/img/annotator-glyph-sprite.png
GuorenWangLianghuaKetangBangzhuWendang/img/annotator-icon-sprite.png
GuorenWangLianghuaKetangBangzhuWendang/img/apple-touch-icon.png
GuorenWangLianghuaKetangBangzhuWendang/img/cancelfullscreen.png
GuorenWangLianghuaKetangBangzhuWendang/img/close.png
GuorenWangLianghuaKetangBangzhuWendang/img/fullscreen.png
GuorenWangLianghuaKetangBangzhuWendang/img/loader.gif
GuorenWangLianghuaKetangBangzhuWendang/img/menu-icon.png
GuorenWangLianghuaKetangBangzhuWendang/img/save.png
GuorenWangLianghuaKetangBangzhuWendang/img/saved.png
GuorenWangLianghuaKetangBangzhuWendang/img/settings-s.png
GuorenWangLianghuaKetangBangzhuWendang/img/settings.png
GuorenWangLianghuaKetangBangzhuWendang/img/star.png
GuorenWangLianghuaKetangBangzhuWendang/js/__init__.py
GuorenWangLianghuaKetangBangzhuWendang/js/epub.js
GuorenWangLianghuaKetangBangzhuWendang/js/epub.min.js
GuorenWangLianghuaKetangBangzhuWendang/js/epub.min.map
GuorenWangLianghuaKetangBangzhuWendang/js/hooks.min.js
GuorenWangLianghuaKetangBangzhuWendang/js/hooks.min.map
guoren_wang_lianghua_ketang_bangzhu_wendang-2024.3.4.0.dist-info/METADATA
guoren_wang_lianghua_ketang_bangzhu_wendang-2024.3.4.0.dist-info/WHEEL
guoren_wang_lianghua_ketang_bangzhu_wendang-2024.3.4.0.dist-info/entry_points.txt
guoren_wang_lianghua_ketang_bangzhu_wendang-2024.3.4.0.dist-info/top_level.txt
guoren_wang_lianghua_ketang_bangzhu_wendang-2024.3.4.0.dist-info/RECORD
